{
    "showroom": {
        "account": {
            "orRegisterLink": "register",
            "loginHeader": "Login",
            "orderStatus": "-",
            "orderItemColumnDate": "Date:",
            "overviewChangeBilling": "Edit address",
            "overviewChangeShipping": "Edit address",
            "loginOrRegisterHeadline": "Login or register"
        },
        "footer": {
            "includeVat": "* All prices incl. value added tax",
            "excludeVat": "* All prices excl. value added tax"
        },
        "general": {
            "offcanvasCloseMenu": "Close",
            "mainMenu": "Menu",
            "privacyNotice": "<a data-toggle=\"modal\" data-url=\"%url%\" href=\"%url%\" title=\"Data protection information\">I have read the data protection information</a>."
        },
        "listing": {
            "boxAddProduct": "Add to cart"
        },
        "detail": {
            "quantity": "Quantity"
        },
        "checkout": {
            "finishButtonBackToShop": "Go to homepage",
            "summaryPositionPrice": "item total",
            "summaryTotalPrice": "Total",
            "summaryTax": "including %rate%% VAT",
            "confirmAddress": "Addresses",
            "confirmPaymentShipping": "Payment & Shipping",
            "confirmChangeShipping": "Edit Shipping",
            "confirmChangePayment": "Edit Payment",
            "confirmSubmit": "Send Order",
            "finishCartHeader": "Your Order",
            "addressLoginToggle": "If you already have an account.",
            "registerHeader": "Register"
        },
        "navigation": {
            "title": "Categories"
        }
    },
    "footer": {
        "newsletterHeadline": "Newsletter",
        "newsletterYourEmail": "Your email address",
        "newsletterInfo": "Subscribe to the free newsletter and ensure that you will no longer miss any offers or news of %shopname%.",
        "serviceHotline": "<a href=\"tel:+49180000000\">0180 - 000000</a> Mon-Fri, 9 am - 5 pm",
        "serviceContactLink": "<a data-toggle=\"modal\" data-url=\"%url%\" href=\"%url%\" title=\"contact form\">Or via our contact form</a>."
    }
}
